nikl/__init__.py
nikl/option.py
nikl/loader/__init__.py
nikl/loader/loadfile.py
nikl/preprocessor/__init__.py
nikl/preprocessor/num.py
nikl/preprocessor/specificChar.py
nikl/target/__init__.py
nikl/target/contents.py
nikl/target/infos.py
nikl-1.1.0.dist-info/LICENSE
nikl-1.1.0.dist-info/METADATA
nikl-1.1.0.dist-info/WHEEL
nikl-1.1.0.dist-info/top_level.txt
nikl-1.1.0.dist-info/RECORD
