Metadata-Version: 2.1
Name: nikl
Version: 1.1.0
Summary: Preprocess NIKL(National Institute of Korean Language) Corpus files
Home-page: https://github.com/study-artificial-intelligence/nikl
Author: Kyeongnam Kim
Author-email: kkyy0126@naver.com
License: MIT
Platform: UNKNOWN
Classifier: Development Status :: 5 - Production/Stable
Classifier: Programming Language :: Python :: 3
Classifier: License :: OSI Approved :: MIT License
Classifier: Natural Language :: Korean
Classifier: Operating System :: Microsoft :: Windows
Classifier: Operating System :: MacOS
Classifier: Operating System :: POSIX
Requires-Python: >=3.6
Requires-Dist: beautifulsoup4
